Metadata-Version: 2.1
Name: opensv
Version: 0.0.1
Summary: An Open-Source Framework for Shapley-based value intened intended for data valuation.
Home-page: https://github.com/ZJU-DIVER/OpenSV
Author: Haocheng Xia, Qiheng Sun, Xiang Li, Yuanzhi Xiao, Hongwei Zhang
Author-email: "Haocheng Xia, Qiheng Sun, Xiang Li, Yuanzhi Xiao, Hongwei Zhang" <xiahc@zju.edu.cn>
License: Apache 2.0
Project-URL: Documentation, https://opensv.readthedocs.io
Project-URL: Source, https://github.com/ZJU-DIVER/OpenSV
Classifier: License :: OSI Approved :: Apache Software License
Classifier: Operating System :: OS Independent
Classifier: Programming Language :: Python
Classifier: Programming Language :: Python :: 3
Classifier: Programming Language :: Python :: 3.10
Classifier: Programming Language :: Python :: 3.11
Classifier: Programming Language :: Python :: 3 :: Only
Requires-Python: >=3.10
Provides-Extra: security
Provides-Extra: socks
Provides-Extra: use_chardet_on_py3
License-File: LICENSE
